dinger_payment/__init__.py
dinger_payment/decrypt.py
dinger_payment/encrypt.py
dinger_payment/prebuild.py
dinger_payment/py.typed
dinger_payment-2.0.8.dist-info/METADATA
dinger_payment-2.0.8.dist-info/WHEEL
dinger_payment-2.0.8.dist-info/RECORD
