Metadata-Version: 2.4
Name: dinger-payment
Version: 2.0.8
Summary: This library purpose is helper for dinger payment encryption
Author-email: Agga <hanzawnyineonline@gmail.com>
Requires-Python: >=3.7
Requires-Dist: pycryptodome==3.21.0
